users_db/__init__.py
users_db/alembic.ini
users_db/commands.py
users_db/config.py
users_db/db.py
users_db/errors.py
users_db/migrations/README.md
users_db/migrations/__init__.py
users_db/migrations/env.py
users_db/migrations/script.py.mako
users_db/migrations/versions/2023_05_15_1207-27133ce191df_add_users_and_role_permissions_tables.py
users_db/pagination.py
users_db/role_permissions.py
users_db/schema.py
users_db/users.py
users_db/utils.py
users_db-0.0.15.dist-info/METADATA
users_db-0.0.15.dist-info/WHEEL
users_db-0.0.15.dist-info/entry_points.txt
users_db-0.0.15.dist-info/RECORD
