Metadata-Version: 2.1
Name: users-db
Version: 0.0.15
Summary: user_db is a database package for user CRUD operations
Author: Bohdan Stratila
Author-email: bogdanstratila@icloud.com
Requires-Python: >=3.10,<4.0
Classifier: Programming Language :: Python :: 3
Classifier: Programming Language :: Python :: 3.10
Classifier: Programming Language :: Python :: 3.11
Requires-Dist: alembic (==1.9.4)
Requires-Dist: black (==23.1.0)
Requires-Dist: click (>=8.1.3,<9.0.0)
Requires-Dist: flake8 (==6.0.0)
Requires-Dist: psycopg2-binary (==2.9.5)
Requires-Dist: pytest (==7.2.1)
Requires-Dist: pytest-cov (>=4.0.0,<5.0.0)
Requires-Dist: sqlalchemy (>=2.0.4,<3.0.0)
